./.gitignore
./PKG-INFO
./README.md
./dumpy.py
./pyproject.toml
dumpy_numpy-0.1.4.dist-info/METADATA
dumpy_numpy-0.1.4.dist-info/WHEEL
dumpy_numpy-0.1.4.dist-info/RECORD
