Metadata-Version: 2.4
Name: dumpy-numpy
Version: 0.1.4
Summary: DumPy: NumPy except it's OK if you're dum
Requires-Python: >=3.8
Requires-Dist: jax
Requires-Dist: numpy
